MANIFEST.in
setup.cfg
setup.py
bin/hatch
etc/bash/hatch.sh
etc/zsh/_hatch
hatch/__init__.py
hatch/config.py
hatch/version.py
hatch/aws/__init__.py
hatch/aws/apigateway.py
hatch/aws/awslambda.py
hatch/aws/cloudfront.py
hatch/aws/iam.py
hatch/aws/route53.py
hatch/aws/s3.py
hatch/aws/utils.py
hatch/services/__init__.py
hatch/services/api.py
hatch/services/website.py
hatch/ux/__init__.py
hatch/ux/server.py
hatch/ux/website.py
hatch_cli.egg-info/PKG-INFO
hatch_cli.egg-info/SOURCES.txt
hatch_cli.egg-info/dependency_links.txt
hatch_cli.egg-info/requires.txt
hatch_cli.egg-info/top_level.txt