Metadata-Version: 1.1
Name: hatch-cli
Version: 1.0.2
Summary: Command line interface for hatch.sh
Home-page: https://github.com/hatch-sh/hatch
Author: Mads Hartmann Jensen
Author-email: mads379@gmail.com
License: MIT
Download-URL: https://github.com/hatch-sh/hatch/archive/1.0.2.tar.gz
Platform: UNKNOWN
